admin_toolbox/__init__.py
admin_toolbox/apps.py
admin_toolbox/settings.py
admin_toolbox/builders/__init__.py
admin_toolbox/builders/base.py
admin_toolbox/builders/generic.py
admin_toolbox/builders/models.py
admin_toolbox/static/admin_sidebar/css/admin-sidebar.css
admin_toolbox/static/admin_sidebar/css/admin-sidebar.css.map
admin_toolbox/static/admin_sidebar/css/admin-sidebar.scss
admin_toolbox/static/admin_sidebar/font-awesome/css/all.css
admin_toolbox/static/admin_sidebar/font-awesome/css/all.min.css
admin_toolbox/static/admin_sidebar/font-awesome/css/brands.css
admin_toolbox/static/admin_sidebar/font-awesome/css/brands.min.css
admin_toolbox/static/admin_sidebar/font-awesome/css/fontawesome.css
admin_toolbox/static/admin_sidebar/font-awesome/css/fontawesome.min.css
admin_toolbox/static/admin_sidebar/font-awesome/css/regular.css
admin_toolbox/static/admin_sidebar/font-awesome/css/regular.min.css
admin_toolbox/static/admin_sidebar/font-awesome/css/solid.css
admin_toolbox/static/admin_sidebar/font-awesome/css/solid.min.css
admin_toolbox/static/admin_sidebar/font-awesome/css/v4-shims.css
admin_toolbox/static/admin_sidebar/font-awesome/css/v4-shims.min.css
admin_toolbox/static/admin_sidebar/font-awesome/sprites/brands.svg
admin_toolbox/static/admin_sidebar/font-awesome/sprites/regular.svg
admin_toolbox/static/admin_sidebar/font-awesome/sprites/solid.svg
admin_toolbox/static/admin_sidebar/font-awesome/webfonts/fa-brands-400.eot
admin_toolbox/static/admin_sidebar/font-awesome/webfonts/fa-brands-400.svg
admin_toolbox/static/admin_sidebar/font-awesome/webfonts/fa-brands-400.ttf
admin_toolbox/static/admin_sidebar/font-awesome/webfonts/fa-brands-400.woff
admin_toolbox/static/admin_sidebar/font-awesome/webfonts/fa-brands-400.woff2
admin_toolbox/static/admin_sidebar/font-awesome/webfonts/fa-regular-400.eot
admin_toolbox/static/admin_sidebar/font-awesome/webfonts/fa-regular-400.svg
admin_toolbox/static/admin_sidebar/font-awesome/webfonts/fa-regular-400.ttf
django_admin_toolbox-1.0.0.dev29.dist-info/LICENSE.txt
django_admin_toolbox-1.0.0.dev29.dist-info/METADATA
django_admin_toolbox-1.0.0.dev29.dist-info/WHEEL
django_admin_toolbox-1.0.0.dev29.dist-info/top_level.txt
django_admin_toolbox-1.0.0.dev29.dist-info/RECORD
