Metadata-Version: 2.1
Name: django-admin-toolbox
Version: 1.0.0.dev29
Summary: Django admin toolbox - bunch of improvements for default django admin
Home-page: https://github.com/gbdlin/django-admin-toolbox
Author: GwynBleidD
Author-email: gbd.lin@gmail.com
License: MIT
Keywords: django admin toolbox sidebar tools improvements
Platform: UNKNOWN
Classifier: Development Status :: 2 - Pre-Alpha
Classifier: Environment :: Web Environment
Classifier: Intended Audience :: Developers
Classifier: Intended Audience :: System Administrators
Classifier: Topic :: Internet :: WWW/HTTP
Classifier: Topic :: Internet :: WWW/HTTP :: Site Management
Classifier: Topic :: Software Development :: User Interfaces
Classifier: Framework :: Django :: 1.10
Classifier: Framework :: Django :: 1.11
Classifier: License :: OSI Approved :: MIT License
Classifier: Operating System :: OS Independent
Classifier: Programming Language :: Python
Classifier: Programming Language :: Python :: 2
Classifier: Programming Language :: Python :: 2.7
Classifier: Programming Language :: Python :: 3
Classifier: Programming Language :: Python :: 3.4
Classifier: Programming Language :: Python :: 3.5
Classifier: Programming Language :: Python :: 3.6
Classifier: Programming Language :: Python :: 3.7
Requires-Python: >=2.7, !=3.0.*, !=3.1.*, !=3.2.*, !=3.3.*, <4
License-File: LICENSE.txt
Requires-Dist: six
Provides-Extra: smart-breadcrumbs
Requires-Dist: beautifulsoup4 ; extra == 'smart-breadcrumbs'
